devoe/__init__.py
devoe/config.py
devoe/dates.py
devoe/log.py
devoe/meta.py
devoe/pipeline.py
devoe/queue.py
devoe/share.py
devoe/step.py
devoe/task.py
devoe/utils.py
devoe/items/__init__.py
devoe/items/items.py
devoe/nodes/__init__.py
devoe/nodes/database/__init__.py
devoe/nodes/database/convs.py
devoe/nodes/database/db.py
devoe/nodes/database/utils.py
devoe/nodes/host/__init__.py
devoe/nodes/host/host.py
devoe/sql/__init__.py
devoe/sql/ddl.py
devoe/sql/dml.py
devoe/sql/func.py
devoe-0.1.0.dist-info/LICENSE
devoe-0.1.0.dist-info/METADATA
devoe-0.1.0.dist-info/WHEEL
devoe-0.1.0.dist-info/top_level.txt
devoe-0.1.0.dist-info/RECORD
