Metadata-Version: 2.1
Name: devoe
Version: 0.1.0
Summary: Python ETL framework.
Home-page: https://github.com/t3eHawk/devoe
Author: Timur Faradzhov
Author-email: timurfaradzhov@gmail.com
License: MIT
Platform: UNKNOWN
Classifier: Programming Language :: Python :: 3
Classifier: License :: OSI Approved :: MIT License
Classifier: Operating System :: OS Independent
Requires-Dist: pepperoni
Requires-Dist: sqlalchemy
Requires-Dist: cx-Oracle
Requires-Dist: paramiko
